bssbridge/__init__.py
bssbridge/__main__.py
bssbridge/commands/dbf/__init__.py
bssbridge/lib/__init__.py
bssbridge/lib/ftp/__init__.py
bssbridge/lib/pool/__init__.py
bssbridge-0.1.10.dist-info/entry_points.txt
bssbridge-0.1.10.dist-info/WHEEL
bssbridge-0.1.10.dist-info/METADATA
bssbridge-0.1.10.dist-info/RECORD
