Metadata-Version: 2.1
Name: bssbridge
Version: 0.1.10
Summary: Робот доставки данных в систему BSS
Author: Anton Rastyazhenko
Author-email: rastyazhenko.anton@gmail.com
Requires-Python: >=3.8,<4.0
Classifier: Programming Language :: Python :: 3
Classifier: Programming Language :: Python :: 3.8
Classifier: Programming Language :: Python :: 3.9
Requires-Dist: aioftp (>=0.18.0,<0.19.0)
Requires-Dist: aiohttp (>=3.5.4,<4.0.0)
Requires-Dist: asyncio (>=3.4.3,<4.0.0)
Requires-Dist: bssapi-schemas (>=0.1.0,<0.2.0)
Requires-Dist: cleo (>=0.8.1,<0.9.0)
Requires-Dist: lz4 (>=3.1.0,<4.0.0)
Requires-Dist: orjson (>=3.3.1,<4.0.0)
Requires-Dist: pydantic (>=1.6.1,<2.0.0)
Requires-Dist: sentry-sdk (>=0.17.8,<0.18.0)
